pypigz/__init__.py
pypigz/connection.py
pypigz/main.py
pypigz/product.py
pypigz-0.0.6.dist-info/METADATA
pypigz-0.0.6.dist-info/WHEEL
pypigz-0.0.6.dist-info/RECORD
