Metadata-Version: 2.1
Name: pypigz
Version: 0.0.6
Summary: 
Author: Fritz Henrique
Author-email: fritzhenrique.dev@gmail.com
Requires-Python: >=3.12,<4.0
Classifier: Programming Language :: Python :: 3
Classifier: Programming Language :: Python :: 3.12
Requires-Dist: mysql-connector-python (==9.0.0)
Requires-Dist: openpyxl (==3.1.5)
Requires-Dist: pandas (==2.2.2)
Requires-Dist: python-dotenv (==1.0.1)
Requires-Dist: xlrd (==2.0.1)
